{
  "object": "location",
  "name": "a14-roundabout-south-west",
  "displayName": "Milton roundabout",
  "description": "You're on the Milton roundabout.",
  "attributes": {
    "type": "outdoor",
    "vehiclesAllowed": [
      "bike",
      "car",
      "van"
    ]
  },
  "exits": [
    {
      "object": "exit",
      "longname": "Left",
      "direction": "l",
      "source": "a14-roundabout-south-west",
      "destination": "a14-westbound",
      "requiredAction": "drive"
    },
    {
      "object": "exit",
      "longname": "Continue",
      "direction": "c",
      "source": "a14-roundabout-south-west",
      "destination": "a14-roundabout",
      "requiredAction": "drive"
    }
  ],
  "synonyms": [
    "a14",
    "a14 roundabout south west",
    "a14-roundabout-south-west",
    "milton",
    "milton roundabout",
    "roundabout",
    "south",
    "west"
  ]
}