{
  "object": "location",
  "name": "lift-ground-floor",
  "displayName": "Lift",
  "description": "The lift doors automatically close behind you. You're in the ground floor lift. It's quite dark in here and every now and again a disembodied voice chants something about electrical faults.<br>You contemplate pressing the alarm button but it'll only route to a call centre somewhere.",
  "attributes": {
    "imageName": "liftdoor.jpg"
  },
  "exits": [
    {
      "object": "exit",
      "longname": "out",
      "direction": "o",
      "source": "lift-ground-floor",
      "destination": "atrium",
      "hidden": true
    },
    {
      "object": "exit",
      "longname": "up",
      "direction": "u",
      "source": "lift-ground-floor",
      "destination": "lift-first-floor"
    }
  ],
  "inventory": [
    {
      "file": "alarm-button"
    },
    {
      "file": "exit-button"
    },
    {
      "file": "led-lift-ground-floor"
    },
    {
      "object": "artefact",
      "template": "mirror",
      "description": "lift mirror",
      "detailedDescription": "Something about this view troubles you.",
      "synonyms": [
        "lift mirror",
        "full mirror"
      ]
    }
  ]
}