{
    "object": "artefact",
    "name": "sugar",
    "description": "sugar",
    "detailedDescription": "Not so good for the waistline but sugary, sweet and tasty.",
    "attributes": {
      "weight": 0.1,
      "type": "food",
      "imageName": "sugar.jpg", 
      "requiresContainer": true,
      "isPowder": true,
      "canCollect": true,
      "charges": 3,
      "chargeUnit": "spoonful",
      "chargesDescription": "There's about $charges $chargeUnit left",
      "combinesDescription": "Don't waste it all, you'll need this as a sweetener",
      "affinityModifier": 0,
      "isEdible": true,
      "nutrition": 5,
      "hideDeliveryDescription":  true,
      "smell": "It's just sugar.",
      "taste": "It's sweet and crunchy in your mouth.",
      "combinesWith": [
          "coffee",
          "latte",
          "mocha"
      ]
    },
  "delivers": [
    {
      "object": "artefact",
      "template": "sweet-coffee"
    },
    {
      "object": "artefact",
      "template": "sweet-latte"
    },
    {
      "object": "artefact",
      "template": "sweet-mocha"
    }
  ],
  "synonyms": ["sweetener"]
}